video_clipper/__init__.py
video_clipper/__main__.py
video_clipper/app.py
video_clipper/data/manifest.sample.yaml
video_clipper_r-0.2.2.dist-info/LICENSE
video_clipper_r-0.2.2.dist-info/METADATA
video_clipper_r-0.2.2.dist-info/WHEEL
video_clipper_r-0.2.2.dist-info/top_level.txt
video_clipper_r-0.2.2.dist-info/RECORD
