Metadata-Version: 2.1
Name: video-clipper-r
Version: 0.2.2
Summary: Clips multiple video clips from one video file.
Author-email: Andrija Junzki <andrew.junzki@gmail.com>
Maintainer-email: Andrija Junzki <andrew.junzki@gmail.com>
Project-URL: Homepage, https://github.com/Junzki/video-clipper
Project-URL: Repository, https://github.com/Junzki/video-clipper.git
Project-URL: Issues, https://github.com/Junzki/video-clipper/issues
Project-URL: Changelog, https://github.com/Junzki/video-clipper/blob/master/CHANGELOG.md
Keywords: video,ffmpeg,clip
Classifier: Development Status :: 4 - Beta
Classifier: Intended Audience :: End Users/Desktop
Classifier: Topic :: Multimedia :: Video
Classifier: Topic :: Multimedia :: Video :: Conversion
Classifier: License :: OSI Approved :: GNU General Public License v3 (GPLv3)
Classifier: Programming Language :: Python :: 3
Requires-Python: >=3.8
License-File: LICENSE
Requires-Dist: PyYAML
